cosmic_web_classifier/__init__.py
cosmic_web_classifier-1.0.1.dist-info/LICENSE
cosmic_web_classifier-1.0.1.dist-info/METADATA
cosmic_web_classifier-1.0.1.dist-info/WHEEL
cosmic_web_classifier-1.0.1.dist-info/top_level.txt
cosmic_web_classifier-1.0.1.dist-info/RECORD
