Metadata-Version: 2.1
Name: cosmic-web-classifier
Version: 1.0.1
Summary: A Python package for classifying cosmic web structures
Author-email: Yangyao Chen <yangyaochen.astro@foxmail.com>
Project-URL: Repository, https://github.com/ChenYangyao/cosmic-web-classifier.git
Classifier: Programming Language :: Python :: 3
Classifier: License :: OSI Approved :: MIT License
Classifier: Operating System :: OS Independent
Requires-Python: >=3.11
License-File: LICENSE
Requires-Dist: pyhipp
Requires-Dist: pytest >=7.0.0
Requires-Dist: flake8
